Metadata-Version: 2.1
Name: zescator
Version: 1.0
Summary: great obfuscation module
Home-page: https://github.com/zeroo-0/obfuscator
Author: zeroo
Author-email: d3ath.runs@gmail.com
License: MIT
Keywords: python obfuscator
Classifier: Development Status :: 3 - Alpha
Classifier: Intended Audience :: Developers
Classifier: License :: OSI Approved :: MIT License
Classifier: Programming Language :: Python :: 3
License-File: LICENSE
